xtrading_models/__init__.py
xtrading_models/bar.py
xtrading_models/execution_result.py
xtrading_models/fill.py
xtrading_models/order.py
xtrading_models-0.6.0.dist-info/licenses/LICENSE
xtrading_models-0.6.0.dist-info/METADATA
xtrading_models-0.6.0.dist-info/WHEEL
xtrading_models-0.6.0.dist-info/top_level.txt
xtrading_models-0.6.0.dist-info/RECORD
