Metadata-Version: 2.4
Name: xtrading-models
Version: 0.6.0
Summary: Shared trading models for XTrading ecosystem
Author-email: Yanir Taflev <yanirta+xtrading@gmail.com>
License: MIT
Keywords: trading,models,finance,algotrading,backtesting
Classifier: Programming Language :: Python :: 3.9
Classifier: Programming Language :: Python :: 3.10
Classifier: Programming Language :: Python :: 3.11
Classifier: License :: OSI Approved :: MIT License
Classifier: Operating System :: OS Independent
Requires-Python: >=3.10
License-File: LICENSE
Requires-Dist: pydantic>=2.0
Provides-Extra: dev
Requires-Dist: pytest; extra == "dev"
Dynamic: license-file
